src/FluidCubeGame/FluidCube.py
src/FluidCubeGame/__init__.py
src/FluidCubeGame/main.py
FluidCubeGame-1.1.4.dist-info/METADATA
FluidCubeGame-1.1.4.dist-info/WHEEL
FluidCubeGame-1.1.4.dist-info/top_level.txt
FluidCubeGame-1.1.4.dist-info/RECORD
