Metadata-Version: 2.1
Name: FluidCubeGame
Version: 1.1.4
Summary: FluidCubeGame
Home-page: https://github.com/Spektoruk3/PAK
Author: Leshin Vladimir, Spektoruk Ilya, Krukovskiy Vasiliy
Author-email: i.spektoruk@g.nsu.ru
Requires-Dist: numpy
Requires-Dist: pygame
